LICENSE.md
dysco/__init__.py
dysco/dysco.py
dysco/scope.py
dysco-0.0.8.dist-info/LICENSE.md
dysco-0.0.8.dist-info/WHEEL
dysco-0.0.8.dist-info/METADATA
dysco-0.0.8.dist-info/RECORD
