Metadata-Version: 2.1
Name: dysco
Version: 0.0.8
Summary: Dysco provides configurable dynamic scoping behavior in Python.
Home-page: https://github.com/intoli/dysco/
License: BSD-2-Clause
Keywords: dynamic scope
Author: Evan Sangaline
Author-email: evan@intoli.com
Requires-Python: >=3.6,<4.0
Classifier: License :: OSI Approved :: BSD License
Classifier: Programming Language :: Python :: 3
Classifier: Programming Language :: Python :: 3.6
Classifier: Programming Language :: Python :: 3.7
Classifier: Programming Language :: Python :: 3.8
Classifier: Topic :: Software Development :: Libraries
Requires-Dist: python-slugify (>=4.0,<5.0)
Project-URL: Repository, https://github.com/intoli/dysco/
